{
	"configurations" : 
	[
		{
			"directories" : 
			[
				{
					"build" : ".",
					"projectIndex" : 0,
					"source" : ".",
					"targetIndexes" : 
					[
						0
					]
				}
			],
			"name" : "Debug",
			"projects" : 
			[
				{
					"directoryIndexes" : 
					[
						0
					],
					"name" : "hello_world",
					"targetIndexes" : 
					[
						0
					]
				}
			],
			"targets" : 
			[
				{
					"directoryIndex" : 0,
					"id" : "hello_world::@6890427a1f51a3e7e1df",
					"jsonFile" : "target-hello_world-Debug-ff537d9559aaefbce427.json",
					"name" : "hello_world",
					"projectIndex" : 0
				}
			]
		}
	],
	"kind" : "codemodel",
	"paths" : 
	{
		"build" : "/home/victor/Documents/ucode/half-marathon-cpp/sprint-00/t00/build",
		"source" : "/home/victor/Documents/ucode/half-marathon-cpp/sprint-00/t00"
	},
	"version" : 
	{
		"major" : 2,
		"minor" : 0
	}
}
